[{"Latitude":29.828119,"gender":"Genderqueer","Name":"Common turkey","Longitude":107.140088},
{"Latitude":58.4286125,"gender":"Genderqueer","Name":"American black bear","Longitude":24.498407},
{"Latitude":10.5289556,"gender":"Genderqueer","Name":"Coke's hartebeest","Longitude":-73.7242486},
{"Latitude":33.9485698,"gender":"Non-binary","Name":"White-eye, pale","Longitude":44.9159938},
{"Latitude":55.3734577,"gender":"Genderfluid","Name":"Fox, north american red","Longitude":26.2092274},
{"Latitude":37.473022,"gender":"Genderfluid","Name":"Two-toed sloth","Longitude":116.603883},
{"Latitude":57.6902027,"gender":"Genderqueer","Name":"Shrike, crimson-breasted","Longitude":11.9070339},
{"Latitude":50.9996233,"gender":"Agender","Name":"Penguin, magellanic","Longitude":26.750679},
{"Latitude":33.006729,"gender":"Bigender","Name":"Zorro, common","Longitude":114.362379},
{"Latitude":-40.6032394,"gender":"Male","Name":"Hornbill, red-billed","Longitude":175.3756249},
{"Latitude":35.669294,"gender":"Bigender","Name":"Lesser masked weaver","Longitude":115.517845},
{"Latitude":52.1565353,"gender":"Agender","Name":"South African hedgehog","Longitude":46.9612179},
{"Latitude":55.0488923,"gender":"Genderfluid","Name":"Goldeneye, barrows","Longitude":41.1651836},
{"Latitude":49.0226173,"gender":"Bigender","Name":"Spoonbill, white","Longitude":1.1394024},
{"Latitude":-6.13333,"gender":"Non-binary","Name":"Woolly-necked stork","Longitude":39.28333},
{"Latitude":24.488342,"gender":"Non-binary","Name":"Cottonmouth","Longitude":110.395104},
{"Latitude":57.7868036,"gender":"Genderfluid","Name":"Burmese brown mountain tortoise","Longitude":38.4503218},
{"Latitude":31.105555,"gender":"Non-binary","Name":"Trumpeter, dark-winged","Longitude":111.214922},
{"Latitude":52.406614,"gender":"Non-binary","Name":"Galapagos mockingbird","Longitude":22.2424971},
{"Latitude":-21.1877747,"gender":"Agender","Name":"Mississippi alligator","Longitude":-41.8799408}]